input_analyzor/__init__.py
input_analyzor/input_analyzor.py
input_analyzor-0.0.2.dist-info/LICENSE
input_analyzor-0.0.2.dist-info/METADATA
input_analyzor-0.0.2.dist-info/WHEEL
input_analyzor-0.0.2.dist-info/top_level.txt
input_analyzor-0.0.2.dist-info/RECORD
